MANIFEST.in
README.md
setup.py
./gevault/gevault
gevault/__init__.py
gevault/__main__.py
gevault.egg-info/PKG-INFO
gevault.egg-info/SOURCES.txt
gevault.egg-info/dependency_links.txt
gevault.egg-info/requires.txt
gevault.egg-info/top_level.txt
gevault/lib/__init__.py
gevault/lib/admin.py
gevault/lib/refresh.py
gevault/lib/tester.py
gevault/lib/users.py
gevault/lib/vault.py
gevault/lib/tester_stack/__init__.py
gevault/lib/tester_stack/nat_cloudformation.yml
gevault/lib/tester_stack/stack.py
gevault/lib/tester_stack/user_data_cloudformation.yml
gevault/test/__init__.py
gevault/test/test_vault.py