Metadata-Version: 2.1
Name: gevault
Version: 1.2.1646754310
Summary: Python Library for communicating with vault server.
Home-page: https://github.build.ge.com/Cloudpod/vault
Author: Barry Howard
Author-email: barry.howard@ge.com
License: UNKNOWN
Keywords: vault,ge,cloudops
Platform: UNKNOWN
